nsj_integracao_api_entidades/__init__.py
nsj_integracao_api_entidades/auth.py
nsj_integracao_api_entidades/config.py
nsj_integracao_api_entidades/db_pool_config.py
nsj_integracao_api_entidades/entity_registry.py
nsj_integracao_api_entidades/injector_factory.py
nsj_integracao_api_entidades/settings.py
nsj_integracao_api_entidades/controller/__init__.py
nsj_integracao_api_entidades/controller/compras_associacoesitensnotas.py
nsj_integracao_api_entidades/controller/compras_negociacoes.py
nsj_integracao_api_entidades/controller/compras_negociacoesfornecedores.py
nsj_integracao_api_entidades/controller/compras_negociacoesitens.py
nsj_integracao_api_entidades/controller/compras_negociacoesvalores.py
nsj_integracao_api_entidades/controller/compras_propostascotacoes.py
nsj_integracao_api_entidades/controller/compras_requisicoescompras.py
nsj_integracao_api_entidades/controller/compras_requisicoesfornecedores.py
nsj_integracao_api_entidades/controller/compras_solicitacoesprodutosservicos.py
nsj_integracao_api_entidades/controller/controller_util.py
nsj_integracao_api_entidades/controller/crm_assuntos.py
nsj_integracao_api_entidades/controller/crm_itensprocessarcontaspagar.py
nsj_integracao_api_entidades/controller/crm_midiasorigem.py
nsj_integracao_api_entidades/controller/crm_negociosoperacoes.py
nsj_integracao_api_entidades/controller/crm_objetosservicoshistoricoscomponentes.py
nsj_integracao_api_entidades/controller/crm_objetosservicoshistoricosofertas.py
nsj_integracao_api_entidades/controller/crm_parcelamentos.py
nsj_integracao_api_entidades/controller/crm_parcelas.py
nsj_integracao_api_entidades/controller/crm_promocoesleads.py
nsj_integracao_api_entidades/controller/crm_proximoscontatos.py
nsj_integracao_api_entidades/controller/crm_segmentosatuacao.py
nsj_integracao_api_entidades/controller/estoque_categoriasdeprodutos.py
nsj_integracao_api_entidades/controller/estoque_classificacoesfragilidade.py
nsj_integracao_api_entidades/controller/estoque_entregadores.py
nsj_integracao_api_entidades-2.0.0a1.dist-info/METADATA
nsj_integracao_api_entidades-2.0.0a1.dist-info/WHEEL
nsj_integracao_api_entidades-2.0.0a1.dist-info/top_level.txt
nsj_integracao_api_entidades-2.0.0a1.dist-info/RECORD
