Metadata-Version: 2.4
Name: nsj_integracao_api_entidades
Version: 2.0.0a1
Summary: Biblioteca que fornece modelos e estruturas padronizadas para facilitar a integração entre sistemas via APIs RESTful.
Home-page: https://github.com/Nasajon/nsj_integracao_api_entidades
Author: Nasajon Sistemas
Author-email: contact.dev@nasajon.com.br
Project-URL: Source, https://github.com/Nasajon/nsj_integracao_api_entidades
Classifier: Development Status :: 3 - Alpha
Classifier: Intended Audience :: Developers
Classifier: Topic :: Software Development :: Libraries
Classifier: Programming Language :: Python :: 3
Requires-Python: >=3.4
Requires-Dist: inflect==6.0.5
Requires-Dist: SQLAlchemy==1.4.32
Requires-Dist: pg8000==1.24.1
Requires-Dist: Flask<3.0.0,>=2.0.3
Requires-Dist: nsj_gcf_utils==1.0.19
Requires-Dist: nsj_rest_lib==2.13.0a14
Requires-Dist: nsj_flask_auth==0.8.0
Requires-Dist: authlib==1.0.0
Requires-Dist: werkzeug==2.0.3
